.DS_Store
sshdocker/__init__.py
sshdocker/api.py
sshdocker/client.py
sshdocker/models.py
sshdocker/ssh.py
sshdocker/utils.py
ssh_docker-1.2.2.dist-info/LICENSE
ssh_docker-1.2.2.dist-info/METADATA
ssh_docker-1.2.2.dist-info/WHEEL
ssh_docker-1.2.2.dist-info/entry_points.txt
ssh_docker-1.2.2.dist-info/top_level.txt
ssh_docker-1.2.2.dist-info/RECORD
