Metadata-Version: 2.1
Name: ssh-docker
Version: 1.2.2
Summary: A small convenience command to interactively deal with containers running remotely.
Home-page: UNKNOWN
Author: Simon Coulton
Author-email: simon@bespohk.com
License: Copyright (c) 2018-2019 Bespohk, and is maintained by multiple
Requires-Dist: click (>=7.0)
Requires-Dist: colorama (>=0.4.1)
Requires-Dist: paramiko (>=2.4.2)
